mucri/__init__.py
mucri/mucri.py
mucri-0.0.9.dist-info/METADATA
mucri-0.0.9.dist-info/WHEEL
mucri-0.0.9.dist-info/top_level.txt
mucri-0.0.9.dist-info/RECORD
