Metadata-Version: 2.1
Name: mucri
Version: 0.0.9
Summary: Quickly fetch multiple pages
Home-page: https://github.com/meain/mucri
Author: Abin Simon
Author-email: abinsimon10@gmail.com
License: UNKNOWN
Keywords: asyncio,scraper,aiohttp
Platform: UNKNOWN
Classifier: Programming Language :: Python
Classifier: Programming Language :: Python :: 3
Classifier: Programming Language :: Python :: 3.5
Classifier: Programming Language :: Python :: 3.6
Classifier: Intended Audience :: Developers
Classifier: License :: OSI Approved :: MIT License
Classifier: Topic :: Software Development :: Libraries
Classifier: Topic :: Utilities
Classifier: Environment :: Console
Classifier: Intended Audience :: End Users/Desktop
Classifier: Topic :: Software Development :: Libraries :: Python Modules
Classifier: Operating System :: POSIX
Classifier: Natural Language :: English
Requires-Dist: aiohttp
